[{"model": "users.user", "pk": 1, "fields": {"password": "pbkdf2_sha256$600000$jKTngyRxZWGFl4U10JP00F$EYaRCJwCaIrTP/tQLwI9cVR/n1LM1aUBt16DzdNuZso=", "last_login": "2023-07-30T11:31:30.351Z", "is_superuser": true, "username": "admin", "first_name": "", "last_name": "", "email": "", "is_staff": true, "is_active": true, "date_joined": "2023-07-15T11:36:45Z", "access": 1, "imns": 1, "groups": [], "user_permissions": []}}, {"model": "users.user", "pk": 3, "fields": {"password": "pbkdf2_sha256$600000$c8MrV9TOVU10uQP7o5l44e$JQ0Q4bLCIvJZpX5O4B1GRhhW9iyYhzhyKicZ8cxrwhk=", "last_login": "2023-07-17T12:44:40.199Z", "is_superuser": false, "username": "imns301", "first_name": "", "last_name": "", "email": "", "is_staff": false, "is_active": true, "date_joined": "2023-07-15T13:35:13.803Z", "access": 1, "imns": 1, "groups": [], "user_permissions": []}}]